zurcolor/__init__.py
zurcolor/colors.py
zurcolor-0.1.1.dist-info/licenses/LICENSE
zurcolor-0.1.1.dist-info/METADATA
zurcolor-0.1.1.dist-info/WHEEL
zurcolor-0.1.1.dist-info/top_level.txt
zurcolor-0.1.1.dist-info/RECORD
