Metadata-Version: 2.4
Name: zurcolor
Version: 0.1.1
Summary: A tiny library for terminal text customisation
Author-email: zurek <julekziolkowski01@gmail.com>
License: Apache-2.0
Project-URL: Homepage, https://pypi.org/project/zurcolor/
Classifier: Programming Language :: Python :: 3
Classifier: License :: OSI Approved :: Apache Software License
Classifier: Operating System :: OS Independent
Requires-Python: >=3.7
License-File: LICENSE
Dynamic: license-file
